{
  "en": {
    "week_started_title": "Football Week Has Begun",
    "week_started_msg": "Make sure to submit your predictions for the upcoming matches!",
    "prediction_score_title": "Unbelievable",
    "prediction_score_msg": "You have predicted the score of the match.",
    "prediction_winner_title": "Congratulations",
    "prediction_winner_msg": "You have predicted the winner of the match.",
    "prediction_draw_title": "Congratulations",
    "prediction_draw_msg": "You have predicted the draw in the match.",
    "cl_started_title": "Les grandes équipes: The champions!",
    "cl_started_msg": "The road to glory begins today! Get your predictions in and compete for the top spot!",
    "mortal_kombat": "Mortal Kombat at",
    "special_match_msg": "Earn 10 points by correctly predicting the match score!",
    "nl_start_title": "The Nations League is back today!",
    "nl_start_msg": "Make your predictions now and compete for the top spot in the tournament. Don't miss out on earning points!",
    "update_title": "el Torneo - League 2 Now Available",
    "update_msg": "Update now for all the latest details.",
    "quest_title": "Attention: Quest match!",
    "quest_msg": "These rare matches require a prediction; otherwise, you’ll lose 3 points.",
    "elclasico_title": "El Clasico: Real Madrid vs Barcelona",
    "elclasico_msg": "The time has come to choose the winner.",
    "seriea_title": "The Scudetto fight continues",
    "seriea_msg": "Make sure to submit your predictions today.",
    "match_title": "Deadpool: Liverpool - PSG",
    "match_msg2": "Make your prediction now.",
    "match_msg": "The match is about to begin. Make your prediction now.",
    "preview_title": "Matchday Video Highlights",
    "preview_msg": "Catch the video highlights from today's matches now!",
    "league2_title": "Join League 2",
    "league2_msg": "If your score is below 20 points, consider moving to League 2 where you can have a better chance to compete for the top spot.",
    "leader_title": "Danijel Radoslovic is back on the throne!",
    "leader_msg": "The new leader of el Torneo!",
    "beat_bet_title": "Today's AI Predictions (Beta)",
    "beat_bet_msg": "Bayern Munich to win (90%), Girona to win (90%), Verona to avoid defeat (91%)"
  },
  "ru": {
    "week_started_title": "Футбольная неделя началась",
    "week_started_msg": "Не забудьте сделать прогнозы на предстоящие матчи!",
    "prediction_score_title": "Невероятно",
    "prediction_score_msg": "Вы предсказали счет матча.",
    "prediction_winner_title": "Поздравляем",
    "prediction_winner_msg": "Вы предсказали победителя матча.",
    "prediction_draw_title": "Поздравляем",
    "prediction_draw_msg": "Вы предсказали ничью в матче.",
    "cl_started_title": "Les grandes équipes: The champions!",
    "cl_started_msg": "Путь к славе начинается сегодня! Делайте прогнозы и соревнуйтесь за первое место!",
    "mortal_kombat": "Смертельная битва на",
    "special_match_msg": "Заработайте 10 очков, правильно предсказав счет матча!",
    "nl_start_title": "Лига Наций возвращается сегодня!",
    "nl_start_msg": "Делайте прогнозы сейчас и соревнуйтесь за первое место в турнире. Не упустите возможность заработать очки!",
    "update_title": "el Torneo - Лига 2 теперь доступна",
    "update_msg": "Обновите приложение, чтобы получить все самые свежие детали.",
    "quest_title": "Внимание: Квест-матч!",
    "quest_msg": "Эти редкие матчи требуют прогноза; в противном случае вы потеряете 3 очка.",
    "elclasico_title": "El Clasico: Real Madrid vs Barcelona",
    "elclasico_msg": "Пришло время выбрать победителя.",
    "seriea_title": "Борьба за Скудетто продолжается",
    "seriea_msg": "Не забудьте подать свои прогнозы сегодня.",
    "match_title": "Deadpool: Liverpool - PSG",
    "match_msg2": "Сделайте ваш прогноз сейчас.",
    "match_msg": "Матч скоро начнется! Сделайте ваш прогноз сейчас.",
    "preview_title": "Обзор матчей",
    "preview_msg": "Смотрите видеообзор предыдущих матчей прямо сейчас!",
    "league2_title": "Перейдите в Лигу 2",
    "league2_msg": "Если ваш счет ниже 20 очков, рассмотрите возможность перехода в Лигу 2, где у вас будет больше шансов побороться за первое место.",
    "leader_title": "Danijel Radoslovic снова на троне!",
    "leader_msg": "Новый лидер el Torneo!",
    "beat_bet_title": "Сегодняшние прогнозы ИИ (Бета)",
    "beat_bet_msg": "Победа Баварии (90%), победа Жироны (90%), Верона не проиграет (91%)"
  },
  "es": {
    "week_started_title": "La semana de fútbol ha comenzado",
    "week_started_msg": "¡Asegúrate de enviar tus predicciones para los próximos partidos!",
    "prediction_score_title": "Increíble",
    "prediction_score_msg": "Has pronosticado el resultado del partido.",
    "prediction_winner_title": "Enhorabuena",
    "prediction_winner_msg": "Has pronosticado el ganador del partido.",
    "prediction_draw_title": "Enhorabuena",
    "prediction_draw_msg": "Has pronosticado el empate del partido.",
    "cl_started_title": "Les grandes équipes: The champions!",
    "cl_started_msg": "¡El camino a la gloria comienza hoy! ¡Haz tus predicciones y compite por el primer puesto!",
    "mortal_kombat": "Mortal Kombat en",
    "special_match_msg": "¡Gana 10 puntos al predecir correctamente el marcador del partido!",
    "nl_start_title": "¡Hoy vuelve la Liga de Naciones!",
    "nl_start_msg": "¡Haz tus predicciones ahora y compite por el primer puesto del torneo. No te quedes sin puntos!",
    "update_title": "el Torneo - Liga 2 ya disponible",
    "update_msg": "Actualiza ahora para obtener todos los detalles más recientes.",
    "quest_title": "¡Atención: Partido Quest!",
    "quest_msg": "Estos partidos raros requieren una predicción; de lo contrario, perderás 3 puntos.",
    "elclasico_title": "El Clasico: Real Madrid vs Barcelona",
    "elclasico_msg": "Es momento de elegir un ganador.",
    "seriea_title": "La lucha por el Scudetto continúa",
    "seriea_msg": "Asegúrate de enviar tus predicciones hoy.",
    "match_title": "Deadpool: Liverpool - PSG",
    "match_msg2": "Haz tu predicción ahora.",
    "match_msg": "¡El partido está a punto de comenzar! Haz tu predicción ahora.",
    "preview_title": "Resumen de partidos",
    "preview_msg": "Mira el resumen en video de los partidos anteriores ahora mismo.",
    "league2_title": "Únete a la Liga 2",
    "league2_msg": "Si tu puntuación es inferior a 20 puntos, considera la posibilidad de unirte a la Liga 2, donde tendrás una mejor oportunidad de competir por el primer puesto.",
    "leader_title": "Danijel Radoslovic vuelve al trono!",
    "leader_msg": "¡El nuevo líder de el Torneo!",
    "beat_bet_title": "Predicciones de IA de hoy (Beta)",
    "beat_bet_msg": "Bayern Múnich ganará (90%), Girona ganará (90%), Verona no perderá (91%)"
  },
  "it": {
    "week_started_title": "La settimana del calcio è iniziata",
    "week_started_msg": "Assicurati di inviare le tue previsioni per le prossime partite!",
    "prediction_score_title": "Incredibile",
    "prediction_score_msg": "Hai previsto il punteggio della partita.",
    "prediction_winner_title": "Congratulazioni",
    "prediction_winner_msg": "Hai previsto il vincitore della partita.",
    "prediction_draw_title": "Congratulazioni",
    "prediction_draw_msg": "Hai previsto il pareggio nella partita.",
    "cl_started_title": "Les grandes équipes: The champions!",
    "cl_started_msg": "La strada per la gloria inizia oggi! Invia i tuoi pronostici e gareggia per il primo posto!",
    "mortal_kombat": "Mortal Kombat a",
    "special_match_msg": "Guadagna 10 punti prevedendo correttamente il punteggio della partita!",
    "nl_start_title": "Oggi torna la Nations League!",
    "nl_start_msg": "Fai subito i tuoi pronostici e gareggia per il primo posto nel torneo. Non perdere l'occasione di guadagnare punti!",
    "update_title": "el Torneo - Lega 2 ora disponibile",
    "update_msg": "Aggiorna ora per tutti i dettagli più recenti.",
    "quest_title": "Attenzione: Partita Quest!",
    "quest_msg": "Queste partite rare richiedono una previsione; altrimenti, perderai 3 punti.",
    "elclasico_title": "El Clasico: Real Madrid vs Barcelona",
    "elclasico_msg": "È il momento di scegliere un vincitore.",
    "seriea_title": "La lotta per lo Scudetto continua",
    "seriea_msg": "Assicurati di inviare i tuoi pronostici oggi.",
    "match_title": "Deadpool: Liverpool - PSG",
    "match_msg2": "Fai la tua previsione ora.",
    "match_msg": "La partita sta per iniziare! Fai la tua previsione ora.",
    "preview_title": "Highlights delle partite",
    "preview_msg": "Guarda gli highlights video delle partite precedenti subito!",
    "league2_title": "Unisciti alla Lega 2",
    "league2_msg": "Se il tuo punteggio è inferiore a 20 punti, considera la possibilità di passare alla Lega 2, dove avrai maggiori possibilità di competere per il primo posto.",
    "leader_title": "Danijel Radoslovic torna sul trono!",
    "leader_msg": "Il nuovo leader di el Torneo!",
    "beat_bet_title": "Previsioni AI di oggi (Beta)",
    "beat_bet_msg": "Bayern Monaco vincerà (90%), Girona vincerà (90%), Verona non perderà (91%)"
  },
  "de": {
    "week_started_title": "Die Fußballwoche hat begonnen",
    "week_started_msg": "Stelle sicher, dass du deine Vorhersagen für die kommenden Spiele abgibst!",
    "prediction_score_title": "Unglaublich",
    "prediction_score_msg": "Sie haben das Ergebnis des Spiels vorhergesagt.",
    "prediction_winner_title": "Herzlichen Glückwunsch",
    "prediction_winner_msg": "Sie haben den Sieger des Spiels vorhergesagt.",
    "prediction_draw_title": "Herzlichen Glückwunsch",
    "prediction_draw_msg": "Sie haben das Unentschieden im Spiel vorhergesagt.",
    "cl_started_title": "Les grandes équipes: The champions!",
    "cl_started_msg": "Der Weg zum Ruhm beginnt heute! Geben Sie Ihre Tipps ab und kämpfen Sie um den Spitzenplatz!",
    "mortal_kombat": "Mortal Kombat bei",
    "special_match_msg": "Erhalte 10 Punkte, indem du das Endergebnis des Spiels korrekt vorhersagst!",
    "nl_start_title": "Die Nations League ist heute zurück!",
    "nl_start_msg": "Geben Sie jetzt Ihre Vorhersagen ab und kämpfen Sie um den Spitzenplatz im Turnier. Verpassen Sie es nicht, Punkte zu sammeln!",
    "update_title": "el Torneo - Liga 2 jetzt verfügbar",
    "update_msg": "Jetzt aktualisieren, um alle neuesten Details zu erhalten.",
    "quest_title": "Achtung: Quest-Spiel!",
    "quest_msg": "Diese seltenen Spiele erfordern eine Vorhersage; andernfalls verlieren Sie 3 Punkte.",
    "elclasico_title": "El Clasico: Real Madrid vs Barcelona",
    "elclasico_msg": "Es ist Zeit, einen Gewinner auszuwählen.",
    "seriea_title": "Der Kampf um den Scudetto geht weiter",
    "seriea_msg": "Vergiss nicht, heute deine Tipps abzugeben.",
    "match_title": "Deadpool: Liverpool - PSG",
    "match_msg2": "Gib jetzt deine Vorhersage ab.",
    "match_msg": "Das Spiel beginnt gleich! Gib jetzt deine Vorhersage ab.",
    "preview_title": "Spiel-Highlights",
    "preview_msg": "Schau dir jetzt die Video-Highlights der vorherigen Spiele an!",
    "league2_title": "Wechsel in die Liga 2",
    "league2_msg": "Wenn deine Punktzahl unter 20 liegt, erwäge den Wechsel in die Liga 2, wo du bessere Chancen hast, um den ersten Platz zu kämpfen.",
    "leader_title": "Danijel Radoslovic ist zurück auf dem Thron!",
    "leader_msg": "Der neue Anführer von el Torneo!",
    "beat_bet_title": "Heutige KI-Vorhersagen (Beta)",
    "beat_bet_msg": "Bayern München gewinnt (90%), Girona gewinnt (90%), Verona verliert nicht (91%)"
  },
  "hr": {
    "week_started_title": "Nogometni tjedan je počeo",
    "week_started_msg": "Obavezno pošaljite svoje prognoze za nadolazeće utakmice!",
    "prediction_score_title": "Nevjerojatno",
    "prediction_score_msg": "Predvidjeli ste rezultat utakmice.",
    "prediction_winner_title": "Čestitamo",
    "prediction_winner_msg": "Predvidjeli ste pobjednika utakmice.",
    "prediction_draw_title": "Čestitamo",
    "prediction_draw_msg": "Predvidjeli ste neodlučeno u utakmici.",
    "cl_started_title": "Les grandes équipes: The champions!",
    "cl_started_msg": "Put do slave počinje danas! Uključite svoja predviđanja i natječite se za prvo mjesto!",
    "mortal_kombat": "Mortal Kombat na",
    "special_match_msg": "Zaradi 10 bodova točno predviđajući rezultat utakmice!",
    "nl_start_title": "Danas se vraća Liga nacija!",
    "nl_start_msg": "Predviđajte sada i natječite se za prvo mjesto na turniru. Ne propustite osvojiti bodove!",
    "update_title": "el Torneo - Liga 2 sada dostupna",
    "update_msg": "Ažuriraj sada za sve najnovije detalje.",
    "quest_title": "Pažnja: Quest utakmica!",
    "quest_msg": "Ove rijetke utakmice zahtijevaju prognozu; u suprotnom ćete izgubiti 3 boda.",
    "elclasico_title": "El Clasico: Real Madrid vs Barcelona",
    "elclasico_msg": "Vrijeme je da izaberemo pobjednika.",
    "seriea_title": "Borba za Scudetto se nastavlja",
    "seriea_msg": "Ne zaboravi poslati svoje prognoze danas.",
    "match_title": "Deadpool: Liverpool - PSG",
    "match_msg2": "Napravite svoju prognozu sada.",
    "match_msg": "Utakmica uskoro počinje! Napravite svoju prognozu sada.",
    "preview_title": "Pregled utakmica",
    "preview_msg": "Pogledajte video pregled prethodnih utakmica odmah!",
    "league2_title": "Pridruži se Ligi 2",
    "league2_msg": "Ako imaš manje od 20 bodova, razmisli o prelasku u Ligu 2, gdje ćeš imati bolju šansu za natjecanje za prvo mjesto.",
    "leader_title": "Danijel Radoslovic se vratio na tron!",
    "leader_msg": "Novi vođa el Tornea!",
    "beat_bet_title": "Današnje AI prognoze (Beta)",
    "beat_bet_msg": "Bayern München pobjeđuje (90%), Girona pobjeđuje (90%), Verona ne gubi (91%)"
  },
  "fr": {
    "week_started_title": "La semaine de football a commencé",
    "week_started_msg": "Assurez-vous de soumettre vos prédictions pour les prochains matchs !",
    "prediction_score_title": "Incroyable",
    "prediction_score_msg": "Vous avez prédit le score du match.",
    "prediction_winner_title": "Félicitations",
    "prediction_winner_msg": "Vous avez prédit le gagnant du match.",
    "prediction_draw_title": "Félicitations",
    "prediction_draw_msg": "Vous avez prédit le match nul.",
    "cl_started_title": "Les grandes équipes: The champions!",
    "cl_started_msg": "Le chemin vers la gloire commence aujourd'hui ! Faites vos prédictions et competez pour la première place !",
    "mortal_kombat": "Mortal Kombat à",
    "special_match_msg": "Gagnez 10 points en prédisant correctement le score du match !",
    "nl_start_title": "La Ligue des Nations est de retour aujourd'hui !",
    "nl_start_msg": "Faites vos prédictions maintenant et competez pour la première place du tournoi. Ne manquez pas l'occasion de gagner des points !",
    "update_title": "el Torneo - Ligue 2 maintenant disponible",
    "update_msg": "Mettez à jour maintenant pour tous les derniers détails.",
    "quest_title": "Attention : Match Quest !",
    "quest_msg": "Ces matchs rares nécessitent une prédiction ; sinon, vous perdrez 3 points.",
    "elclasico_title": "El Clasico: Real Madrid vs Barcelona",
    "elclasico_msg": "Il est temps de choisir un gagnant.",
    "seriea_title": "La lutte pour le Scudetto continue",
    "seriea_msg": "N'oubliez pas de soumettre vos pronostics aujourd'hui.",
    "match_title": "Deadpool: Liverpool - PSG",
    "match_msg2": "Faites votre prédiction maintenant.",
    "match_msg": "Le match est sur le point de commencer ! Faites votre prédiction maintenant.",
    "preview_title": "Résumé des matchs",
    "preview_msg": "Regardez dès maintenant les vidéos des matchs précédents !",
    "league2_title": "Rejoignez la Ligue 2",
    "league2_msg": "Si vous avez moins de 20 points, envisagez de rejoindre la Ligue 2, où vous aurez une meilleure chance de concourir pour la première place.",
    "leader_title": "Danijel Radoslovic est de retour sur le trône !",
    "leader_msg": "Le nouveau leader de el Torneo !",
    "beat_bet_title": "Prédictions IA du jour (Bêta)",
    "beat_bet_msg": "Bayern Munich gagne (90%), Girona gagne (90%), Vérone ne perd pas (91%)"
  },
  "pt": {
    "week_started_title": "A semana de futebol começou",
    "week_started_msg": "Certifique-se de enviar suas previsões para os próximos jogos!",
    "prediction_score_title": "Inacreditável",
    "prediction_score_msg": "Você previu o resultado da partida.",
    "prediction_winner_title": "Parabéns",
    "prediction_winner_msg": "Você previu o vencedor da partida.",
    "prediction_draw_title": "Parabéns",
    "prediction_draw_msg": "Você previu o empate na partida.",
    "cl_started_title": "Les grandes équipes: The champions!",
    "cl_started_msg": "O caminho para a glória começa hoje! Faça suas previsões e dispute o primeiro lugar!",
    "mortal_kombat": "Mortal Kombat em",
    "special_match_msg": "Ganhe 10 pontos prevendo corretamente o resultado da partida!",
    "nl_start_title": "A Liga das Nações está de volta hoje!",
    "nl_start_msg": "Faça suas previsões agora e dispute o primeiro lugar no torneio. Não perca a oportunidade de ganhar pontos!",
    "update_title": "el Torneo - Liga 2 agora disponível",
    "update_msg": "Atualize agora para obter todos os detalhes mais recentes.",
    "quest_title": "Atenção: Partida Quest!",
    "quest_msg": "Essas partidas raras exigem uma previsão; caso contrário, você perderá 3 pontos.",
    "elclasico_title": "El Clasico: Real Madrid vs Barcelona",
    "elclasico_msg": "É hora de escolher um vencedor.",
    "seriea_title": "A luta pelo Scudetto continua",
    "seriea_msg": "Não se esqueça de enviar suas previsões hoje.",
    "match_title": "Deadpool: Liverpool - PSG",
    "match_msg2": "Faça sua previsão agora.",
    "match_msg": "A partida está prestes a começar! Faça sua previsão agora.",
    "preview_title": "Resumo das partidas",
    "preview_msg": "Assista agora aos melhores momentos das partidas anteriores!",
    "league2_title": "Junte-se à Liga 2",
    "league2_msg": "Se você tem menos de 20 pontos, considere mudar para a Liga 2, onde terá mais chances de competir pelo primeiro lugar.",
    "leader_title": "Danijel Radoslovic está de volta ao trono!",
    "leader_msg": "O novo líder do el Torneo!",
    "beat_bet_title": "Previsões de IA de hoje (Beta)",
    "beat_bet_msg": "Bayern de Munique vence (90%), Girona vence (90%), Verona não perde (91%)"
  }
}
